{
  "Routes": [
    // Catalog API
    {
      "DownstreamPathTemplate": "/api/v1/Catalog", // where to redirect
      "DownstreamScheme": "http",
      "DownstreamHostAndPorts": [ // redirect host
        {
          "Host": "localhost",
          "Port": "8000"
        }
      ],
      "UpstreamPathTemplate": "/Catalog", // route to gateway
      "UpstreamHttpMethod": [ "GET", "POST", "PUT" ] // accepted method
    },
    {
      "DownstreamPathTemplate": "/api/v1/Catalog/{id}",
      "DownstreamScheme": "http",
      "DownstreamHostAndPorts": [
        {
          "Host": "localhost",
          "Port": "8000"
        }
      ],
      "UpstreamPathTemplate": "/Catalog/{id}",
      "UpstreamHttpMethod": [ "GET", "DELETE" ]
    },
    {
      "DownstreamPathTemplate": "/api/v1/Catalog/GetProductByCategory/{category}",
      "DownstreamScheme": "http",
      "DownstreamHostAndPorts": [
        {
          "Host": "localhost",
          "Port": "8000"
        }
      ],
      "UpstreamPathTemplate": "/Catalog/GetProductByCategory/{category}",
      "UpstreamHttpMethod": [ "GET" ]
    },
    // BASKET API
    {
      "DownstreamPathTemplate": "/api/v1/Basket/{username}",
      "DownstreamScheme": "http",
      "DownstreamHostAndPorts": [
        {
          "Host": "localhost",
          "Port": "8001"
        }
      ],
      "UpstreamPathTemplate": "/Basket/{username}",
      "UpstreamHttpMethod": [ "GET", "DELETE" ]
    },
    {
      "DownstreamPathTemplate": "/api/v1/Basket",
      "DownstreamScheme": "http",
      "DownstreamHostAndPorts": [
        {
          "Host": "localhost",
          "Port": "8001"
        }
      ],
      "UpstreamPathTemplate": "/Basket",
      "UpstreamHttpMethod": [ "POST" ]
    },
    {
      "DownstreamPathTemplate": "/api/v1/Basket/Checkout",
      "DownstreamScheme": "http",
      "DownstreamHostAndPorts": [
        {
          "Host": "localhost",
          "Port": "8001"
        }
      ],
      "UpstreamPathTemplate": "/Basket/Checkout",
      "UpstreamHttpMethod": [ "POST" ]
    },
    // DISCOUNT API
    {
      "DownstreamPathTemplate": "/api/v1/Discount",
      "DownstreamScheme": "http",
      "DownstreamHostAndPorts": [
        {
          "Host": "localhost",
          "Port": "8002"
        }
      ],
      "UpstreamPathTemplate": "/Discount",
      "UpstreamHttpMethod": [ "PUT", "POST" ]
    },
    {
      "DownstreamPathTemplate": "/api/v1/Discount/{productName}",
      "DownstreamScheme": "http",
      "DownstreamHostAndPorts": [
        {
          "Host": "localhost",
          "Port": "8002"
        }
      ],
      "UpstreamPathTemplate": "/Discount/{productName}",
      "UpstreamHttpMethod": [ "GET", "DELETE" ]
    },
    // ORDERING API
    {
      "DownstreamPathTemplate": "/api/v1/Order/{username}",
      "DownstreamScheme": "http",
      "DownstreamHostAndPorts": [
        {
          "Host": "localhost",
          "Port": "8004"
        }
      ],
      "UpstreamPathTemplate": "/Order/{username}",
      "UpstreamHttpMethod": [ "GET" ]
    }
  ],
  "GlobalConfiguration": {
    "BaseUrl": "http://localhost:5010" // where is our api gateway is served
  }
}
